imecilabt/gpulab/cli/__init__.py
imecilabt/gpulab/cli/__main__.py
imecilabt/gpulab/cli/_version.py
imecilabt/gpulab/cli/apiclient.py
imecilabt/gpulab/cli/cert_processor.py
imecilabt/gpulab/cli/ssh_config_manager.py
imecilabt/gpulab/cli/util.py
imecilabt_gpulab_cli-3.11.11.dist-info/licenses/LICENSE
imecilabt_gpulab_cli-3.11.11.dist-info/METADATA
imecilabt_gpulab_cli-3.11.11.dist-info/WHEEL
imecilabt_gpulab_cli-3.11.11.dist-info/entry_points.txt
imecilabt_gpulab_cli-3.11.11.dist-info/top_level.txt
imecilabt_gpulab_cli-3.11.11.dist-info/RECORD
