Metadata-Version: 2.4
Name: imecilabt-gpulab-cli
Version: 3.11.11
Summary: GPULab CLI
Home-page: https://gpulab.ilabt.imec.be
Author: Thijs Walcarius <Thijs.Walcarius@ugent.be>, Wim Van de Meerssche <wim.vandemeerssche@ugent.be>
Author-email: gpulab@ilabt.imec.be
License: GPLv3
Project-URL: Bug Tracker, https://gitlab.ilabt.imec.be/ilabt/gpulab/gpulab-cli/-/issues
Project-URL: Documentation, https://doc.ilabt.imec.be/ilabt/gpulab/
Project-URL: Website, https://gpulab.ilabt.imec.be
Project-URL: Source, https://gitlab.ilabt.imec.be/ilabt/gpulab/gpulab-cli
Classifier: Development Status :: 5 - Production/Stable
Classifier: Programming Language :: Python :: 3
Classifier: Programming Language :: Python :: 3.10
Classifier: License :: OSI Approved :: GNU General Public License v3 (GPLv3)
Classifier: Intended Audience :: Science/Research
Classifier: Topic :: Scientific/Engineering
Classifier: Operating System :: POSIX :: Linux
Requires-Python: >=3.10
License-File: LICENSE
Requires-Dist: requests==2.31.0
Requires-Dist: click>=6.7
Requires-Dist: cryptography==3.4.8
Requires-Dist: imecilabt-gpulab-common<7,>=6.0.11
Requires-Dist: pydantic[email]<3,>=2.11.7
Requires-Dist: pytz
Dynamic: author
Dynamic: author-email
Dynamic: classifier
Dynamic: description
Dynamic: description-content-type
Dynamic: home-page
Dynamic: license
Dynamic: license-file
Dynamic: project-url
Dynamic: requires-dist
Dynamic: requires-python
Dynamic: summary
